[
  {
    "name": "Jest",
    "ring": "adopt",
    "quadrant": "tools",
    "isNew": "TRUE",
    "description": "Although the idea of dependency management ..."
  },
  {
    "name": "WebdriverIO",
    "ring": "trial",
    "quadrant": "techniques",
    "isNew": "FALSE",
    "description": "Many projects have external code dependencies ..."
  },
  {
    "name": "Playwright",
    "ring": "assess",
    "quadrant": "platforms",
    "isNew": "TRUE",
    "description": "Apache Kylin is an open source analytics solution ..."
  },
  {
    "name": "Axios",
    "ring": "hold",
    "quadrant": "languages & frameworks",
    "isNew": "FALSE",
    "description": "We continue to see teams run into trouble using JSF ..."
  },
  {
    "name": "Java",
    "ring": "hold",
    "quadrant": "something",
    "isNew": "TRUE",
    "description": "We continue to see teams run into trouble using JSF ..."
  }
]
